tests/timechimp/__init__.py
tests/timechimp/api/__init__.py
tests/timechimp/api/test_customers.py
tests/timechimp/api/test_expenses.py
tests/timechimp/api/test_invoices.py
tests/timechimp/api/test_mileage.py
tests/timechimp/api/test_project_notes.py
tests/timechimp/api/test_project_tasks.py
tests/timechimp/api/test_project_users.py
tests/timechimp/api/test_projects.py
tests/timechimp/api/test_tags.py
tests/timechimp/api/test_tasks.py
tests/timechimp/api/test_time.py
tests/timechimp/api/test_user_contracts.py
tests/timechimp/api/test_users.py
timechimp/__init__.py
timechimp/_endpoint.py
timechimp/_env_variable.py
timechimp/_request.py
timechimp/_response.py
timechimp/enum.py
timechimp/exceptions.py
timechimp/version.py
timechimp/api/__init__.py
timechimp/api/customers/__init__.py
timechimp/api/customers/_customers.py
timechimp/api/expenses/__init__.py
timechimp/api/expenses/_expenses.py
timechimp/api/invoices/__init__.py
timechimp/api/invoices/_invoices.py
timechimp/api/mileage/__init__.py
timechimp/api/mileage/_mileage.py
timechimp/api/project_notes/__init__.py
timechimp/api/project_notes/_project_notes.py
timechimp/api/project_tasks/__init__.py
timechimp/api/project_tasks/_project_tasks.py
timechimp/api/project_users/__init__.py
timechimp/api/project_users/_project_users.py
timechimp/api/projects/__init__.py
timechimp/api/projects/_projects.py
timechimp/api/tags/__init__.py
timechimp/api/tags/_tags.py
timechimp/api/tasks/__init__.py
timechimp/api/tasks/_tasks.py
timechimp/api/time/__init__.py
timechimp/api/time/_time.py
timechimp/api/user_contracts/__init__.py
timechimp/api/user_contracts/_user_contracts.py
timechimp/api/users/__init__.py
timechimp/api/users/_users.py
timechimp-0.0.12.dist-info/LICENSE
timechimp-0.0.12.dist-info/METADATA
timechimp-0.0.12.dist-info/WHEEL
timechimp-0.0.12.dist-info/top_level.txt
timechimp-0.0.12.dist-info/RECORD
