Metadata-Version: 2.1
Name: timechimp
Version: 0.0.12
Summary: TimeChimp API Python SDK
Home-page: https://github.com/Afilnor/TimeChimp
Author: Florian Dauphin
Author-email: dauphin.florian@gmail.com
License: UNKNOWN
Download-URL: https://github.com/Afilnor/TimeChimp/archive/refs/heads/master.zip
Keywords: timechimp
Platform: any
Classifier: Programming Language :: Python :: 3
Classifier: Operating System :: OS Independent
Requires-Python: >=3.6
Requires-Dist: pytest
Requires-Dist: pytest-cov
Requires-Dist: requests
Requires-Dist: sphinx
Requires-Dist: sphinx-rtd-theme
